iplookup/__init__.py
iplookup_cli-0.1.dist-info/METADATA
iplookup_cli-0.1.dist-info/WHEEL
iplookup_cli-0.1.dist-info/entry_points.txt
iplookup_cli-0.1.dist-info/top_level.txt
iplookup_cli-0.1.dist-info/RECORD
